fenjing/__init__.py
fenjing/__main__.py
fenjing/cli.py
fenjing/config_payload.py
fenjing/const.py
fenjing/context_vars.py
fenjing/cracker.py
fenjing/form.py
fenjing/full_payload_gen.py
fenjing/interact.py
fenjing/job.py
fenjing/mcp_server.py
fenjing/options.py
fenjing/payload_gen.py
fenjing/pbar.py
fenjing/requester.py
fenjing/rules_types.py
fenjing/rules_utils.py
fenjing/scan_url.py
fenjing/shell_payload.py
fenjing/submitter.py
fenjing/waf_func_gen.py
fenjing/webui.py
fenjing/wordlist.py
fenjing/rules/__init__.py
fenjing/rules/basic_syntax.py
fenjing/rules/final_target.py
fenjing/rules/get_attritem.py
fenjing/rules/important_variables.py
fenjing/rules/interger.py
fenjing/rules/list_ops.py
fenjing/rules/string.py
fenjing/rules/string_piece.py
fenjing/static/FiraCodeNerdFontMono-Regular.ttf
fenjing/static/base.css
fenjing/static/base.js
fenjing/templates/base.jinja2
fenjing/templates/crack-json.jinja2
fenjing/templates/crack-path.jinja2
fenjing/templates/crack.jinja2
fenjing/templates/interactive-panel.jinja2
fenjing/templates/scan.jinja2
fenjing-0.9.0.dist-info/licenses/LICENSE
fenjing-0.9.0.dist-info/METADATA
fenjing-0.9.0.dist-info/WHEEL
fenjing-0.9.0.dist-info/entry_points.txt
fenjing-0.9.0.dist-info/top_level.txt
fenjing-0.9.0.dist-info/RECORD
