Metadata-Version: 2.4
Name: fenjing
Version: 0.9.0
Summary: A Jinja SSTI cracker for CTF competitions
Home-page: https://github.com/Marven11/Fenjing
Author: Marven11
Author-email: marven11@example.com
Classifier: Programming Language :: Python :: 3.7
Classifier: License :: OSI Approved :: Mozilla Public License 2.0 (MPL 2.0)
Classifier: Operating System :: OS Independent
License-File: LICENSE
Requires-Dist: requests
Requires-Dist: beautifulsoup4
Requires-Dist: click
Requires-Dist: flask
Requires-Dist: jinja2
Requires-Dist: prompt_toolkit
Requires-Dist: pygments
Requires-Dist: pysocks
Requires-Dist: rich>=12
Provides-Extra: mcp
Requires-Dist: mcp; extra == "mcp"
Dynamic: author
Dynamic: author-email
Dynamic: classifier
Dynamic: description
Dynamic: description-content-type
Dynamic: home-page
Dynamic: license-file
Dynamic: provides-extra
Dynamic: requires-dist
Dynamic: summary
